{"path": ["KS", "Shawnee"], "total_courses": {"2022/01/05": {"Evusheld": 144, "Paxlovid": 40}, "2022/01/07": {"Evusheld": 120, "Molnupiravir": 200, "Paxlovid": 40}, "2022/01/10": {"Evusheld": 192, "Molnupiravir": 200, "Paxlovid": 40}, "2022/01/11": {"Evusheld": 144, "Molnupiravir": 240, "Paxlovid": 40}, "2022/01/12": {"Evusheld": 144, "Molnupiravir": 240, "Paxlovid": 40}, "2022/01/13": {"Evusheld": 144, "Molnupiravir": 240, "Paxlovid": 60}, "2022/01/14": {"Evusheld": 144, "Molnupiravir": 240, "Paxlovid": 60}, "2022/01/19": {"Evusheld": 144, "Molnupiravir": 240, "Paxlovid": 100}}, "courses_delivered": {"2022/01/05": {"Evusheld": 48, "Paxlovid": 0}, "2022/01/07": {"Evusheld": 49, "Molnupiravir": 0, "Paxlovid": 0}, "2022/01/10": {"Evusheld": 74, "Molnupiravir": 0, "Paxlovid": 30}, "2022/01/11": {"Evusheld": 50, "Molnupiravir": 0, "Paxlovid": 39}, "2022/01/12": {"Evusheld": 51, "Molnupiravir": 0, "Paxlovid": 39}, "2022/01/13": {"Evusheld": 28, "Molnupiravir": 0, "Paxlovid": 39}, "2022/01/14": {"Evusheld": 5, "Molnupiravir": 8, "Paxlovid": 39}, "2022/01/19": {"Evusheld": 10, "Molnupiravir": 8, "Paxlovid": 80}}, "courses_available": {"2022/01/05": {"Evusheld": 96, "Paxlovid": 0}, "2022/01/07": {"Evusheld": 71, "Molnupiravir": 0, "Paxlovid": 0}, "2022/01/10": {"Evusheld": 118, "Molnupiravir": 0, "Paxlovid": 10}, "2022/01/11": {"Evusheld": 70, "Molnupiravir": 0, "Paxlovid": 1}, "2022/01/12": {"Evusheld": 69, "Molnupiravir": 0, "Paxlovid": 1}, "2022/01/13": {"Evusheld": 92, "Molnupiravir": 0, "Paxlovid": 1}, "2022/01/14": {"Evusheld": 115, "Molnupiravir": 192, "Paxlovid": 1}, "2022/01/19": {"Evusheld": 110, "Molnupiravir": 192, "Paxlovid": 0}}, "children": {}, "child_treatments": [], "providers": {"2096": {"provider_name": "Dillon Pharmacy 61500067", "address1": "2010 Se 29th St", "address2": "Ste B", "city": "Topeka", "county": "Shawnee", "state_code": "KS", "zip_code": "66605", "lat": 39.015202, "lng": -95.650421, "order_label": "Molnupiravir"}, "2097": {"provider_name": "Cotton O Neil Cancer Center (9008)", "address1": "1500 Sw 10th Avenue", "address2": "Attn: Pharmacy Buyer", "city": "Topeka", "county": "Shawnee", "state_code": "KS", "zip_code": "66604", "lat": 39.051231, "lng": -95.696021, "order_label": "Evusheld"}, "2098": {"provider_name": "Comprehensive Cancer Cntr", "address1": "1700 Sw 7th St.", "address2": null, "city": "Topeka", "county": "Shawnee", "state_code": "KS", "zip_code": "66606", "lat": 39.056107, "lng": -95.696692, "order_label": "Evusheld"}}, "treatments": {"2096": {"Molnupiravir": 192}, "2097": {"Evusheld": 62}, "2098": {"Evusheld": 48}}}