{"path": ["OH", "Hamilton"], "total_courses": {"2022/01/05": {"Evusheld": 888, "Molnupiravir": 1040, "Paxlovid": 180}, "2022/01/07": {"Evusheld": 648, "Molnupiravir": 1040, "Paxlovid": 180}, "2022/01/10": {"Evusheld": 1128, "Molnupiravir": 540, "Paxlovid": 180}, "2022/01/11": {"Evusheld": 648, "Molnupiravir": 1040, "Paxlovid": 180}}, "courses_delivered": {"2022/01/05": {"Evusheld": 0, "Molnupiravir": 0, "Paxlovid": 0}, "2022/01/07": {"Evusheld": 0, "Molnupiravir": 0, "Paxlovid": 0}, "2022/01/10": {"Evusheld": 0, "Molnupiravir": 0, "Paxlovid": 0}, "2022/01/11": {"Evusheld": 96, "Molnupiravir": 500, "Paxlovid": 79}}, "courses_available": {"2022/01/05": {"Evusheld": 0, "Molnupiravir": 0, "Paxlovid": 0}, "2022/01/07": {"Evusheld": 0, "Molnupiravir": 0, "Paxlovid": 0}, "2022/01/10": {"Evusheld": 0, "Molnupiravir": 0, "Paxlovid": 0}, "2022/01/11": {"Evusheld": 120, "Molnupiravir": 0, "Paxlovid": 1}}, "children": {}, "child_treatments": [], "providers": {"914": {"provider_name": "Uc Health Univ Of Cincinnati", "address1": "331 Albert Sabin Way", "address2": null, "city": "Cincinnati", "county": "Hamilton", "state_code": "OH", "zip_code": "45229", "lat": 39.139546, "lng": -84.502349, "order_label": "Evusheld"}}, "treatments": {"914": {"Paxlovid": 1, "Evusheld": 120}}}