{"path": ["IN", "Vanderburgh"], "total_courses": {"2021/12/28": {"Evusheld": 0, "Molnupiravir": 0, "Paxlovid": 0}, "2021/12/29": {"Evusheld": 0, "Molnupiravir": 0, "Paxlovid": 0}, "2021/12/30": {"Evusheld": 0, "Molnupiravir": 0, "Paxlovid": 0}, "2022/01/03": {"Evusheld": 384, "Molnupiravir": 140, "Paxlovid": 100}, "2022/01/04": {"Evusheld": 384, "Molnupiravir": 140, "Paxlovid": 100}, "2022/01/05": {"Evusheld": 720, "Molnupiravir": 140, "Paxlovid": 100}, "2022/01/07": {"Evusheld": 240, "Molnupiravir": 140, "Paxlovid": 60}}, "courses_delivered": {"2021/12/28": {"Evusheld": 0, "Molnupiravir": 0, "Paxlovid": 0}, "2021/12/29": {"Evusheld": 0, "Molnupiravir": 0, "Paxlovid": 0}, "2021/12/30": {"Evusheld": 0, "Molnupiravir": 0, "Paxlovid": 0}, "2022/01/03": {"Evusheld": 96, "Molnupiravir": 0, "Paxlovid": 0}, "2022/01/04": {"Evusheld": 0, "Molnupiravir": 0, "Paxlovid": 0}, "2022/01/05": {"Evusheld": 144, "Molnupiravir": 1, "Paxlovid": 0}, "2022/01/07": {"Evusheld": 48, "Molnupiravir": 5, "Paxlovid": 0}}, "courses_available": {"2021/12/28": {"Evusheld": 0, "Molnupiravir": 0, "Paxlovid": 0}, "2021/12/29": {"Evusheld": 0, "Molnupiravir": 0, "Paxlovid": 0}, "2021/12/30": {"Evusheld": 0, "Molnupiravir": 0, "Paxlovid": 0}, "2022/01/03": {"Evusheld": 288, "Molnupiravir": 0, "Paxlovid": 100}, "2022/01/04": {"Evusheld": 384, "Molnupiravir": 80, "Paxlovid": 100}, "2022/01/05": {"Evusheld": 576, "Molnupiravir": 79, "Paxlovid": 100}, "2022/01/07": {"Evusheld": 192, "Molnupiravir": 75, "Paxlovid": 60}}, "children": {}, "child_treatments": [], "providers": {"ChIJeTmBGyYrbogREYzq5qAOFH8": {"provider_name": "St Vincent Evansville", "address1": "3700 Washington Ave", "address2": null, "city": "Evansville", "county": "Vanderburgh", "state_code": "IN", "zip_code": "47714", "lat": 37.9628438, "lng": -87.49584829999999, "place_id": "ChIJeTmBGyYrbogREYzq5qAOFH8", "order_label": "Evusheld"}, "ChIJbcdLuGrTcYgREhLApHCMP2M": {"provider_name": "Cvs Store #07653", "address1": "5120 Weston Road", "address2": "Cvs Pharmacy", "city": "Evansville", "county": "Vanderburgh", "state_code": "IN", "zip_code": "47712", "lat": 37.9768865, "lng": -87.63810989999999, "place_id": "ChIJbcdLuGrTcYgREhLApHCMP2M", "order_label": "Molnupiravir"}, "ChIJy--81xrVcYgRnrd-CiRm26Y": {"provider_name": "Deaconess Gateway Hospital", "address1": "600 Mary St", "address2": null, "city": "Evansville", "county": "Vanderburgh", "state_code": "IN", "zip_code": "47710", "lat": 37.9830836, "lng": -87.57125649999999, "place_id": "ChIJy--81xrVcYgRnrd-CiRm26Y", "order_label": "Evusheld"}, "ChIJeweEJ8rVcYgRfNoewTVtOkE": {"provider_name": "Cvs Store #06252", "address1": "4480 First Ave.", "address2": "Cvs Pharmacy", "city": "Evansville", "county": "Vanderburgh", "state_code": "IN", "zip_code": "47710", "lat": 38.0189843, "lng": -87.5755002, "place_id": "ChIJeweEJ8rVcYgRfNoewTVtOkE", "order_label": "Molnupiravir"}}, "treatments": {"ChIJeTmBGyYrbogREYzq5qAOFH8": {"Paxlovid": 20, "Evusheld": 48}, "ChIJbcdLuGrTcYgREhLApHCMP2M": {"Molnupiravir": 38}, "ChIJy--81xrVcYgRnrd-CiRm26Y": {"Paxlovid": 40, "Evusheld": 144}, "ChIJeweEJ8rVcYgRfNoewTVtOkE": {"Molnupiravir": 37}}}