{"path": ["WA", "Pierce"], "total_courses": {"2022/01/05": {"Evusheld": 216, "Molnupiravir": 440, "Paxlovid": 100}, "2022/01/07": {"Evusheld": 312, "Molnupiravir": 440, "Paxlovid": 60}, "2022/01/10": {"Evusheld": 312, "Molnupiravir": 440, "Paxlovid": 60}, "2022/01/11": {"Evusheld": 312, "Molnupiravir": 120, "Paxlovid": 80}, "2022/01/12": {"Evusheld": 312, "Molnupiravir": 160, "Paxlovid": 80}, "2022/01/13": {"Evusheld": 312, "Molnupiravir": 420, "Paxlovid": 140}, "2022/01/14": {"Evusheld": 456, "Molnupiravir": 700, "Paxlovid": 180}, "2022/01/19": {"Evusheld": 456, "Molnupiravir": 600, "Paxlovid": 200}, "2022/01/21": {"Evusheld": 504, "Molnupiravir": 620, "Paxlovid": 200}, "2022/01/24": {"Evusheld": 504, "Molnupiravir": 1040, "Paxlovid": 200}, "2022/01/25": {"Evusheld": 888, "Molnupiravir": 1720, "Paxlovid": 280}}, "courses_delivered": {"2022/01/05": {"Evusheld": 48, "Molnupiravir": 0, "Paxlovid": 0}, "2022/01/07": {"Evusheld": 96, "Molnupiravir": 0, "Paxlovid": 0}, "2022/01/10": {"Evusheld": 96, "Molnupiravir": 0, "Paxlovid": 0}, "2022/01/11": {"Evusheld": 96, "Molnupiravir": 0, "Paxlovid": 0}, "2022/01/12": {"Evusheld": 96, "Molnupiravir": 10, "Paxlovid": 0}, "2022/01/13": {"Evusheld": 96, "Molnupiravir": 10, "Paxlovid": 0}, "2022/01/14": {"Evusheld": 144, "Molnupiravir": 110, "Paxlovid": 0}, "2022/01/19": {"Evusheld": 144, "Molnupiravir": 10, "Paxlovid": 20}, "2022/01/21": {"Evusheld": 144, "Molnupiravir": 10, "Paxlovid": 2}, "2022/01/24": {"Evusheld": 144, "Molnupiravir": 10, "Paxlovid": 2}, "2022/01/25": {"Evusheld": 240, "Molnupiravir": 397, "Paxlovid": 25}}, "courses_available": {"2022/01/05": {"Evusheld": 0, "Molnupiravir": 0, "Paxlovid": 0}, "2022/01/07": {"Evusheld": 0, "Molnupiravir": 0, "Paxlovid": 0}, "2022/01/10": {"Evusheld": 0, "Molnupiravir": 0, "Paxlovid": 0}, "2022/01/11": {"Evusheld": 0, "Molnupiravir": 0, "Paxlovid": 0}, "2022/01/12": {"Evusheld": 0, "Molnupiravir": 10, "Paxlovid": 0}, "2022/01/13": {"Evusheld": 0, "Molnupiravir": 30, "Paxlovid": 0}, "2022/01/14": {"Evusheld": 0, "Molnupiravir": 30, "Paxlovid": 0}, "2022/01/19": {"Evusheld": 0, "Molnupiravir": 110, "Paxlovid": 0}, "2022/01/21": {"Evusheld": 0, "Molnupiravir": 130, "Paxlovid": 18}, "2022/01/24": {"Evusheld": 0, "Molnupiravir": 450, "Paxlovid": 18}, "2022/01/25": {"Evusheld": 0, "Molnupiravir": 463, "Paxlovid": 15}}, "children": {}, "child_treatments": [], "providers": {"954": {"provider_name": "Safeway Pharmacy", "address1": "1624 72nd St E", "address2": null, "city": "Tacoma", "county": "Pierce", "state_code": "WA", "zip_code": "98404", "lat": 47.19176, "lng": -122.407303}, "955": {"provider_name": "Sav-on Pharmacy", "address1": "11330 51st Ave", "address2": null, "city": "Gig Harbor", "county": "Pierce", "state_code": "WA", "zip_code": "98332", "lat": 47.360698, "lng": -122.6069}, "956": {"provider_name": "Safeway Pharmacy", "address1": "2411 N Proctor St", "address2": null, "city": "Tacoma", "county": "Pierce", "state_code": "WA", "zip_code": "98406", "lat": 47.269773, "lng": -122.488895}, "957": {"provider_name": "Safeway Pharmacy", "address1": "1302 S 38th St", "address2": null, "city": "Tacoma", "county": "Pierce", "state_code": "WA", "zip_code": "98418", "lat": 47.223146, "lng": -122.4511}, "958": {"provider_name": "Safeway Pharmacy", "address1": "611 S. Meridian", "address2": null, "city": "Puyallup", "county": "Pierce", "state_code": "WA", "zip_code": "98371", "lat": 47.187005, "lng": -122.293666}, "959": {"provider_name": "Safeway Pharmacy", "address1": "5616 176th St E", "address2": null, "city": "Puyallup", "county": "Pierce", "state_code": "WA", "zip_code": "98375", "lat": 47.096381, "lng": -122.353002}, "960": {"provider_name": "Sav-on Pharmacy", "address1": "104 Millitary Rd S", "address2": null, "city": "Tacoma", "county": "Pierce", "state_code": "WA", "zip_code": "98444", "lat": 47.119035, "lng": -122.432776}, "961": {"provider_name": "Safeway Pharmacy", "address1": "1112 South M Street", "address2": null, "city": "Tacoma", "county": "Pierce", "state_code": "WA", "zip_code": "98405", "lat": 47.251268, "lng": -122.454497}, "962": {"provider_name": "Safeway Pharmacy", "address1": "10223 Gravelly Lake Drive Sw", "address2": null, "city": "Lakewood", "county": "Pierce", "state_code": "WA", "zip_code": "98499", "lat": 47.164109, "lng": -122.520641}, "963": {"provider_name": "Safeway Pharmacy", "address1": "13308 Meridian E", "address2": null, "city": "Puyallup", "county": "Pierce", "state_code": "WA", "zip_code": "98373", "lat": 47.135296, "lng": -122.292999}, "964": {"provider_name": "Advanced Familycare Medicine", "address1": "9104 S Tacoma Way", "address2": "Ste 106f", "city": "Lakewood", "county": "Pierce", "state_code": "WA", "zip_code": "98499", "lat": 47.174875, "lng": -122.483762}, "965": {"provider_name": "Safeway Pharmacy", "address1": "2637 N. Pearl Street", "address2": null, "city": "Tacoma", "county": "Pierce", "state_code": "WA", "zip_code": "98407", "lat": 47.272984, "lng": -122.515863}, "966": {"provider_name": "Safeway Pharmacy", "address1": "900 Meridian E Ste 12", "address2": null, "city": "Milton", "county": "Pierce", "state_code": "WA", "zip_code": "98354", "lat": 47.248198, "lng": -122.293822}, "967": {"provider_name": "Safeway Pharmacy", "address1": "4831 Point Fosdick Dr", "address2": null, "city": "Gig Harbor", "county": "Pierce", "state_code": "WA", "zip_code": "98335", "lat": 47.301872, "lng": -122.579183}, "968": {"provider_name": "Safeway Pharmacy", "address1": "10105 224th St E", "address2": null, "city": "Graham", "county": "Pierce", "state_code": "WA", "zip_code": "98338", "lat": 47.053079, "lng": -122.296804}, "969": {"provider_name": "Safeway Pharmacy", "address1": "11501 Canyon Road E.", "address2": null, "city": "Puyallup", "county": "Pierce", "state_code": "WA", "zip_code": "98373", "lat": 47.151886, "lng": -122.357128}}, "treatments": {"954": {"Molnupiravir": 20}, "955": {"Molnupiravir": 20}, "956": {"Molnupiravir": 20}, "957": {"Molnupiravir": 20}, "958": {"Molnupiravir": 20}, "959": {"Molnupiravir": 19}, "960": {"Molnupiravir": 20}, "961": {"Molnupiravir": 20}, "962": {"Molnupiravir": 20}, "963": {"Molnupiravir": 20}, "964": {"Paxlovid": 15}, "965": {"Molnupiravir": 20}, "966": {"Molnupiravir": 9}, "967": {"Molnupiravir": 95}, "968": {"Molnupiravir": 20}, "969": {"Molnupiravir": 120}}}