{"path": ["MN", "Olmsted"], "total_courses": {"2022/01/05": {"Evusheld": 1440, "Molnupiravir": 220, "Paxlovid": 80}, "2022/01/07": {"Evusheld": 720, "Molnupiravir": 220, "Paxlovid": 80}, "2022/01/10": {"Evusheld": 2160, "Molnupiravir": 220, "Paxlovid": 80}, "2022/01/11": {"Evusheld": 1080, "Molnupiravir": 220, "Paxlovid": 80}, "2022/01/12": {"Evusheld": 1080, "Molnupiravir": 220, "Paxlovid": 80}, "2022/01/13": {"Evusheld": 1080, "Molnupiravir": 220, "Paxlovid": 80}, "2022/01/14": {"Evusheld": 1080, "Molnupiravir": 220, "Paxlovid": 80}, "2022/01/19": {"Evusheld": 1272, "Molnupiravir": 480, "Paxlovid": 220}, "2022/01/21": {"Evusheld": 1272, "Molnupiravir": 480, "Paxlovid": 220}, "2022/01/24": {"Evusheld": 1272, "Molnupiravir": 480, "Paxlovid": 220}, "2022/01/25": {"Evusheld": 2184, "Molnupiravir": 960, "Paxlovid": 240}}, "courses_delivered": {"2022/01/05": {"Evusheld": 0, "Molnupiravir": 0, "Paxlovid": 0}, "2022/01/07": {"Evusheld": 0, "Molnupiravir": 0, "Paxlovid": 0}, "2022/01/10": {"Evusheld": 0, "Molnupiravir": 0, "Paxlovid": 0}, "2022/01/11": {"Evusheld": 0, "Molnupiravir": 0, "Paxlovid": 0}, "2022/01/12": {"Evusheld": 0, "Molnupiravir": 0, "Paxlovid": 0}, "2022/01/13": {"Evusheld": 0, "Molnupiravir": 0, "Paxlovid": 2}, "2022/01/14": {"Evusheld": 0, "Molnupiravir": 0, "Paxlovid": 7}, "2022/01/19": {"Evusheld": 0, "Molnupiravir": 220, "Paxlovid": 138}, "2022/01/21": {"Evusheld": 249, "Molnupiravir": 220, "Paxlovid": 24}, "2022/01/24": {"Evusheld": 254, "Molnupiravir": 220, "Paxlovid": 24}, "2022/01/25": {"Evusheld": 1007, "Molnupiravir": 660, "Paxlovid": 24}}, "courses_available": {"2022/01/05": {"Evusheld": 0, "Molnupiravir": 0, "Paxlovid": 0}, "2022/01/07": {"Evusheld": 0, "Molnupiravir": 0, "Paxlovid": 0}, "2022/01/10": {"Evusheld": 0, "Molnupiravir": 0, "Paxlovid": 0}, "2022/01/11": {"Evusheld": 0, "Molnupiravir": 0, "Paxlovid": 0}, "2022/01/12": {"Evusheld": 0, "Molnupiravir": 0, "Paxlovid": 0}, "2022/01/13": {"Evusheld": 0, "Molnupiravir": 220, "Paxlovid": 58}, "2022/01/14": {"Evusheld": 0, "Molnupiravir": 220, "Paxlovid": 53}, "2022/01/19": {"Evusheld": 0, "Molnupiravir": 220, "Paxlovid": 42}, "2022/01/21": {"Evusheld": 1023, "Molnupiravir": 220, "Paxlovid": 156}, "2022/01/24": {"Evusheld": 1018, "Molnupiravir": 220, "Paxlovid": 156}, "2022/01/25": {"Evusheld": 1177, "Molnupiravir": 220, "Paxlovid": 156}}, "children": {}, "child_treatments": [], "providers": {"1392": {"provider_name": "Mayo Clinic Pharmacy Mary Brigh", "address1": "3551 Commercial Drive Sw", "address2": null, "city": "Rochester", "county": "Olmsted", "state_code": "MN", "zip_code": "55902", "lat": 43.970135, "lng": -92.463751}, "1393": {"provider_name": "Mayo Rochester Methodist Hospital", "address1": "201 West Center Street", "address2": "Attn: Ei 1-406 Inpatient Pharmacy", "city": "Rochester", "county": "Olmsted", "state_code": "MN", "zip_code": "55902", "lat": 44.023482, "lng": -92.465915}}, "treatments": {"1392": {"Molnupiravir": 220, "Paxlovid": 156}, "1393": {"Evusheld": 1177}}}