{"path": ["CA", "Orange"], "total_courses": {"2022/01/05": {"Evusheld": 1464, "Molnupiravir": 1460, "Paxlovid": 360}, "2022/01/07": {"Evusheld": 768, "Molnupiravir": 1460, "Paxlovid": 360}, "2022/01/10": {"Evusheld": 1368, "Molnupiravir": 1460, "Paxlovid": 360}}, "courses_delivered": {"2022/01/05": {"Evusheld": 737, "Molnupiravir": 1, "Paxlovid": 166}, "2022/01/07": {"Evusheld": 370, "Molnupiravir": 6, "Paxlovid": 182}, "2022/01/10": {"Evusheld": 788, "Molnupiravir": 13, "Paxlovid": 227}}, "courses_available": {"2022/01/05": {"Evusheld": 535, "Molnupiravir": 659, "Paxlovid": 208}, "2022/01/07": {"Evusheld": 302, "Molnupiravir": 1374, "Paxlovid": 192}, "2022/01/10": {"Evusheld": 580, "Molnupiravir": 1367, "Paxlovid": 133}}, "children": {}, "child_treatments": [], "providers": {"1926": {"provider_name": "Cvs Store #09744", "address1": "1535 East Katella Avenue", "address2": "Cvs Pharmacy", "city": "Orange", "county": "Orange", "state_code": "CA", "zip_code": "92867", "lat": 33.809154, "lng": -117.838335, "order_label": "Paxlovid"}, "1927": {"provider_name": "Cvs Store #08849", "address1": "1545 West 17th Street", "address2": "Cvs Pharmacy", "city": "Santa Ana", "county": "Orange", "state_code": "CA", "zip_code": "92706", "lat": 33.760088, "lng": -117.889771, "order_label": "Molnupiravir"}, "1928": {"provider_name": "Providence Mission Hospital", "address1": "27700 Medical Center Rd", "address2": null, "city": "Mission Viejo", "county": "Orange", "state_code": "CA", "zip_code": "92691", "lat": 33.560152, "lng": -117.666045, "order_label": "Evusheld"}, "1929": {"provider_name": "Cvs Store #09575", "address1": "5501 Ball Road", "address2": "Cvs Pharmacy", "city": "Cypress", "county": "Orange", "state_code": "CA", "zip_code": "90630", "lat": 33.817056, "lng": -118.036023, "order_label": "Paxlovid"}, "1930": {"provider_name": "Cvs Store #09569", "address1": "17136 Magnolia St.", "address2": "Cvs Pharmacy", "city": "Fountain Valley", "county": "Orange", "state_code": "CA", "zip_code": "92708", "lat": 33.714231, "lng": -117.971775, "order_label": "Paxlovid"}, "1931": {"provider_name": "Cvs Store #11111", "address1": "390 N. Brea Blvd", "address2": "Cvs Pharmacy", "city": "Brea", "county": "Orange", "state_code": "CA", "zip_code": "92821", "lat": 33.924569, "lng": -117.89591, "order_label": "Molnupiravir"}, "1932": {"provider_name": "Hoag Mem Hosp Pnb", "address1": "1 Hoag Drive", "address2": null, "city": "Newport Beach", "county": "Orange", "state_code": "CA", "zip_code": "92663", "lat": 33.625136, "lng": -117.931415, "order_label": "Evusheld"}, "1933": {"provider_name": "Cvs Store #08893", "address1": "602 N. El Camino Real", "address2": "Cvs Pharmacy", "city": "San Clemente", "county": "Orange", "state_code": "CA", "zip_code": "92672", "lat": 33.430111, "lng": -117.617574, "order_label": "Molnupiravir"}, "1934": {"provider_name": "Providence St Jude Med Center Chs", "address1": "101 E Valencia Mesa Dr", "address2": null, "city": "Fullerton", "county": "Orange", "state_code": "CA", "zip_code": "92835", "lat": 33.893507, "lng": -117.927836, "order_label": "Evusheld"}, "1935": {"provider_name": "Cvs Store #08861", "address1": "8850 Valley View Street", "address2": "Cvs Pharmacy", "city": "Buena Park", "county": "Orange", "state_code": "CA", "zip_code": "90620", "lat": 33.8338999, "lng": -118.0277081, "order_label": "Paxlovid"}, "1936": {"provider_name": "Cvs Store #09119", "address1": "4040 E. Chapman Ave.", "address2": "Cvs Pharmacy", "city": "Orange", "county": "Orange", "state_code": "CA", "zip_code": "92869", "lat": 33.787764, "lng": -117.809966, "order_label": "Molnupiravir"}, "1937": {"provider_name": "Cvs Store #09598", "address1": "455 North State College Boulevard", "address2": "Cvs Pharmacy", "city": "Fullerton", "county": "Orange", "state_code": "CA", "zip_code": "92831", "lat": 33.873869, "lng": -117.889614, "order_label": "Paxlovid"}, "1938": {"provider_name": "Cvs Store #09583", "address1": "102 North Main Street", "address2": "Cvs Pharmacy", "city": "Santa Ana", "county": "Orange", "state_code": "CA", "zip_code": "92701", "lat": 33.746125, "lng": -117.867637, "order_label": "Molnupiravir"}, "1939": {"provider_name": "Cvs Store #08890", "address1": "17642 East 17th St.", "address2": "Cvs Pharmacy", "city": "Tustin", "county": "Orange", "state_code": "CA", "zip_code": "92780", "lat": 33.759753, "lng": -117.824195, "order_label": "Molnupiravir"}, "1940": {"provider_name": "Childrens Hospital Of Orange County", "address1": "1201 W. La Veta Ave", "address2": null, "city": "Orange", "county": "Orange", "state_code": "CA", "zip_code": "92868", "lat": 33.780332, "lng": -117.865553, "order_label": "Evusheld"}, "1941": {"provider_name": "Cvs Store #10225", "address1": "1803 South Harbor Blvd", "address2": "Cvs Pharmacy", "city": "Anaheim", "county": "Orange", "state_code": "CA", "zip_code": "92802", "lat": 33.803146, "lng": -117.915402, "order_label": "Paxlovid"}, "1942": {"provider_name": "Cvs Store #05841", "address1": "2330 South Main Street", "address2": "Cvs Pharmacy", "city": "Santa Ana", "county": "Orange", "state_code": "CA", "zip_code": "92707", "lat": 33.715263, "lng": -117.868024, "order_label": "Paxlovid"}, "1943": {"provider_name": "Cvs Store #08854", "address1": "1750 North Grand Avenue", "address2": "Cvs Pharmacy", "city": "Santa Ana", "county": "Orange", "state_code": "CA", "zip_code": "92705", "lat": 33.7607684, "lng": -117.8531364, "order_label": "Molnupiravir"}, "1944": {"provider_name": "Cvs Store #09561", "address1": "17625 Harvard Avenue", "address2": "Cvs Pharmacy", "city": "Irvine", "county": "Orange", "state_code": "CA", "zip_code": "92614", "lat": 33.676542, "lng": -117.831643, "order_label": "Molnupiravir"}, "1945": {"provider_name": "Cvs Store #06770", "address1": "22361 Antonio Pkwy.", "address2": "Cvs Pharmacy", "city": "Rancho Santa Margarita", "county": "Orange", "state_code": "CA", "zip_code": "92688", "lat": 33.637895, "lng": -117.589723, "order_label": "Molnupiravir"}, "1946": {"provider_name": "Rite Aid 06472", "address1": "1035 W Orangethorpe Avenue", "address2": null, "city": "Fullerton", "county": "Orange", "state_code": "CA", "zip_code": "92833-4733", "lat": 33.859323, "lng": -117.94274, "order_label": "Molnupiravir"}, "1947": {"provider_name": "Uc Irvine Health", "address1": "101 The City Dr S", "address2": "Bldg 1, Room 1428 (pharmacy)", "city": "Orange", "county": "Orange", "state_code": "CA", "zip_code": "92868", "lat": 33.78867, "lng": -117.890716, "order_label": "Evusheld"}, "1948": {"provider_name": "Cvs Store #09246", "address1": "24167 Paseo De Valencia", "address2": "Cvs Pharmacy", "city": "Laguna Woods", "county": "Orange", "state_code": "CA", "zip_code": "92637", "lat": 33.611464, "lng": -117.71304, "order_label": "Molnupiravir"}, "1949": {"provider_name": "Providence St. Joseph Hospital Oran", "address1": "1100 West Stewart Drive", "address2": null, "city": "Orange", "county": "Orange", "state_code": "CA", "zip_code": "92868", "lat": 33.782363, "lng": -117.864861, "order_label": "Evusheld"}, "1950": {"provider_name": "Cvs Store #08851", "address1": "24271 Muirlands Blvd", "address2": "Cvs Pharmacy", "city": "Lake Forest", "county": "Orange", "state_code": "CA", "zip_code": "92630", "lat": 33.630063, "lng": -117.707018, "order_label": "Molnupiravir"}, "1951": {"provider_name": "Cvs Store #07088", "address1": "16961 Beach Boulevard", "address2": "Cvs Pharmacy", "city": "Huntington Beach", "county": "Orange", "state_code": "CA", "zip_code": "92647", "lat": 33.715969, "lng": -117.98921, "order_label": "Molnupiravir"}, "1952": {"provider_name": "Cvs Store #08862", "address1": "12031 Brookhurst Street", "address2": "Cvs Pharmacy", "city": "Garden Grove", "county": "Orange", "state_code": "CA", "zip_code": "92840", "lat": 33.788135, "lng": -117.958813, "order_label": "Molnupiravir"}}, "treatments": {"1926": {"Molnupiravir": 60, "Paxlovid": 17}, "1927": {"Paxlovid": 7, "Molnupiravir": 60}, "1928": {"Evusheld": 48}, "1929": {"Molnupiravir": 60, "Paxlovid": 2}, "1930": {"Molnupiravir": 60, "Paxlovid": 12}, "1931": {"Paxlovid": 4, "Molnupiravir": 60}, "1932": {"Evusheld": 48}, "1933": {"Molnupiravir": 78}, "1934": {"Evusheld": 48}, "1935": {"Molnupiravir": 80, "Paxlovid": 19}, "1936": {"Paxlovid": 15, "Molnupiravir": 60}, "1937": {"Molnupiravir": 80, "Paxlovid": 15}, "1938": {"Paxlovid": 14, "Molnupiravir": 80}, "1939": {"Paxlovid": 11, "Molnupiravir": 80}, "1940": {"Evusheld": 22}, "1941": {"Molnupiravir": 60, "Paxlovid": 10}, "1942": {"Molnupiravir": 59, "Paxlovid": 7}, "1943": {"Molnupiravir": 60}, "1944": {"Molnupiravir": 56}, "1945": {"Molnupiravir": 60}, "1946": {"Molnupiravir": 60}, "1947": {"Evusheld": 135}, "1948": {"Molnupiravir": 60}, "1949": {"Evusheld": 48}, "1950": {"Molnupiravir": 56}, "1951": {"Molnupiravir": 79}, "1952": {"Molnupiravir": 59}}}