{"path": ["KS", "Sherman"], "total_courses": {"2022/01/05": {"Paxlovid": 20}, "2022/01/07": {"Paxlovid": 20}, "2022/01/10": {"Paxlovid": 20}, "2022/01/11": {"Paxlovid": 20}, "2022/01/12": {"Paxlovid": 20}, "2022/01/13": {"Paxlovid": 20}, "2022/01/14": {"Paxlovid": 20}, "2022/01/19": {"Paxlovid": 40}, "2022/01/21": {"Paxlovid": 40}, "2022/01/24": {"Paxlovid": 40}, "2022/01/25": {"Paxlovid": 60}}, "courses_delivered": {"2022/01/05": {"Paxlovid": 0}, "2022/01/07": {"Paxlovid": 0}, "2022/01/10": {"Paxlovid": 7}, "2022/01/11": {"Paxlovid": 7}, "2022/01/12": {"Paxlovid": 9}, "2022/01/13": {"Paxlovid": 9}, "2022/01/14": {"Paxlovid": 16}, "2022/01/19": {"Paxlovid": 38}, "2022/01/21": {"Paxlovid": 40}, "2022/01/24": {"Paxlovid": 20}, "2022/01/25": {"Paxlovid": 45}}, "courses_available": {"2022/01/05": {"Paxlovid": 0}, "2022/01/07": {"Paxlovid": 0}, "2022/01/10": {"Paxlovid": 13}, "2022/01/11": {"Paxlovid": 13}, "2022/01/12": {"Paxlovid": 11}, "2022/01/13": {"Paxlovid": 11}, "2022/01/14": {"Paxlovid": 4}, "2022/01/19": {"Paxlovid": 2}, "2022/01/21": {"Paxlovid": 0}, "2022/01/24": {"Paxlovid": 20}, "2022/01/25": {"Paxlovid": 15}}, "children": {}, "child_treatments": [], "providers": {"1981": {"provider_name": "Walmart Pharmacy #2562", "address1": "2160 Commerce Rd", "address2": null, "city": "Goodland", "county": "Sherman", "state_code": "KS", "zip_code": "67735", "lat": 39.334057, "lng": -101.726555}}, "treatments": {"1981": {"Paxlovid": 15}}}