{"path": ["LA", "Jefferson Davis"], "total_courses": {"2022/01/05": {"Molnupiravir": 40}, "2022/01/07": {"Molnupiravir": 60}, "2022/01/10": {"Molnupiravir": 60}, "2022/01/11": {"Molnupiravir": 60}, "2022/01/12": {"Molnupiravir": 60}, "2022/01/13": {"Molnupiravir": 60}}, "courses_delivered": {"2022/01/05": {"Molnupiravir": 20}, "2022/01/07": {"Molnupiravir": 20}, "2022/01/10": {"Molnupiravir": 20}, "2022/01/11": {"Molnupiravir": 20}, "2022/01/12": {"Molnupiravir": 20}, "2022/01/13": {"Molnupiravir": 20}}, "courses_available": {"2022/01/05": {"Molnupiravir": 0}, "2022/01/07": {"Molnupiravir": 0}, "2022/01/10": {"Molnupiravir": 0}, "2022/01/11": {"Molnupiravir": 0}, "2022/01/12": {"Molnupiravir": 40}, "2022/01/13": {"Molnupiravir": 40}}, "children": {}, "child_treatments": [], "providers": {"527": {"provider_name": "Cvs Store #04501", "address1": "1204 Elton Rd.", "address2": "Cvs Pharmacy", "city": "Jennings", "county": "Jefferson Davis", "state_code": "LA", "zip_code": "70546", "lat": 30.231805, "lng": -92.663389, "order_label": "Molnupiravir"}, "528": {"provider_name": "Walmart Pharmacy #386", "address1": "303 E Interstate Dr", "address2": null, "city": "Jennings", "county": "Jefferson Davis", "state_code": "LA", "zip_code": "70546", "lat": 30.246245, "lng": -92.658443, "order_label": "Molnupiravir"}}, "treatments": {"527": {"Molnupiravir": 20}, "528": {"Molnupiravir": 20}}}