{"path": ["WI", "Iron"], "total_coures": {"2022/01/05": {"Molnupiravir": 20}}, "courses_delivered": {"2022/01/05": {"Molnupiravir": 0}}, "courses_available": {"2022/01/05": {"Molnupiravir": 0}}, "locations": [{"provider_name": "White Cross Pharmacy", "address1": "314 Silver Street", "address2": null, "city": "Hurley", "county": "Iron", "state_code": "WI", "zip_code": "54534", "lat": null, "lng": null, "place_id": null, "national_drug_code": "0006-5055-06", "order_label": "Molnupiravir", "last_order_date": "2022-01-03T00:00:00", "last_delivered_date": null, "total_courses": 20, "courses_available": null, "courses_available_date": null}], "children": []}