{"path": ["MT", "Prairie"], "total_courses": {"2022/01/26": {"Molnupiravir": 20}, "2022/01/27": {"Molnupiravir": 20}, "2022/01/28": {"Molnupiravir": 40}}, "courses_delivered": {"2022/01/26": {"Molnupiravir": 0}, "2022/01/27": {"Molnupiravir": 0}, "2022/01/28": {"Molnupiravir": 20}}, "courses_available": {"2022/01/26": {"Molnupiravir": 0}, "2022/01/27": {"Molnupiravir": 0}, "2022/01/28": {"Molnupiravir": 20}}, "children": {}, "child_treatments": [], "providers": {"257": {"provider_name": "Prairie County Hospital", "address1": "312 South Adams", "address2": null, "city": "Terry", "county": "Prairie", "state_code": "MT", "zip_code": "59349", "lat": 46.791326, "lng": -105.315991, "order_label": "Molnupiravir"}}, "treatments": {"257": {"Molnupiravir": 20}}}