{"path": ["NE", "Douglas"], "total_coures": {"2021/12/28": {"Evusheld": 0}, "2021/12/29": {"Evusheld": 0, "Molnupiravir": 0, "Paxlovid": 0}, "2021/12/30": {"Evusheld": 0, "Molnupiravir": 0, "Paxlovid": 0}, "2022/01/03": {"Evusheld": 240, "Molnupiravir": 280, "Paxlovid": 100}, "2022/01/04": {"Evusheld": 240, "Molnupiravir": 340, "Paxlovid": 100}, "2022/01/05": {"Evusheld": 240, "Molnupiravir": 340, "Paxlovid": 100}}, "courses_delivered": {"2021/12/28": {"Evusheld": 0}, "2021/12/29": {"Evusheld": 0, "Molnupiravir": 0, "Paxlovid": 0}, "2021/12/30": {"Evusheld": 0, "Molnupiravir": 0, "Paxlovid": 0}, "2022/01/03": {"Evusheld": 27, "Molnupiravir": 0, "Paxlovid": 0}, "2022/01/04": {"Evusheld": 50, "Molnupiravir": 60, "Paxlovid": 0}, "2022/01/05": {"Evusheld": 57, "Molnupiravir": 60, "Paxlovid": 0}}, "courses_available": {"2021/12/28": {"Evusheld": 0}, "2021/12/29": {"Evusheld": 0, "Molnupiravir": 0, "Paxlovid": 0}, "2021/12/30": {"Evusheld": 0, "Molnupiravir": 0, "Paxlovid": 0}, "2022/01/03": {"Evusheld": 213, "Molnupiravir": 0, "Paxlovid": 0}, "2022/01/04": {"Evusheld": 190, "Molnupiravir": 0, "Paxlovid": 0}, "2022/01/05": {"Evusheld": 183, "Molnupiravir": 80, "Paxlovid": 0}}, "locations": [{"provider_name": "Chi Health Pharmacy-bergan Mercy", "address1": "7500 Mercy Road", "address2": "Attn: Inpatient Pharmacy", "city": "Omaha", "county": "Douglas", "state_code": "NE", "zip_code": "68124", "lat": 41.2399087, "lng": -96.03057079999999, "place_id": "ChIJoUXTFKfxk4cRymTCot4rCVs", "national_drug_code": "0006-5055-06", "order_label": "Molnupiravir", "last_order_date": "2021-12-29T00:00:00", "last_delivered_date": null, "total_courses": 60, "courses_available": 0, "courses_available_date": "2022-01-04T00:00:00"}, {"provider_name": "Charles Drew Health Center", "address1": "2915 Grant Street", "address2": null, "city": "Omaha", "county": "Douglas", "state_code": "NE", "zip_code": "68111", "lat": 41.2795432, "lng": -95.9554005, "place_id": "ChIJN6wb8ySOk4cRhDnK0l6NE2s", "national_drug_code": "0069-1085-30", "order_label": "Paxlovid", "last_order_date": "2021-12-28T00:00:00", "last_delivered_date": null, "total_courses": 60, "courses_available": null, "courses_available_date": null}, {"provider_name": "One World Health Centers", "address1": "4920 South 30th Street", "address2": "Suite 103", "city": "Omaha", "county": "Douglas", "state_code": "NE", "zip_code": "68107", "lat": 41.2100115, "lng": -95.95604689999999, "place_id": "ChIJd2YdY8yOk4cREGuafANMTCo", "national_drug_code": "0069-1085-30", "order_label": "Paxlovid", "last_order_date": "2021-12-28T00:00:00", "last_delivered_date": null, "total_courses": 40, "courses_available": null, "courses_available_date": null}, {"provider_name": "Chi Health Pharmacy-bergan Mercy", "address1": "7500 Mercy Road", "address2": "Attn: Inpatient Pharmacy", "city": "Omaha", "county": "Douglas", "state_code": "NE", "zip_code": "68124", "lat": 41.2399087, "lng": -96.03057079999999, "place_id": "ChIJoUXTFKfxk4cRymTCot4rCVs", "national_drug_code": "0310-7442-02", "order_label": "Evusheld", "last_order_date": "2021-12-18T00:00:00", "last_delivered_date": null, "total_courses": 144, "courses_available": 116, "courses_available_date": "2022-01-05T00:00:00"}, {"provider_name": "Nebraska Medicine", "address1": "981090 Nebraska Medical Center", "address2": "Buffett Dock", "city": "Omaha", "county": "Douglas", "state_code": "NE", "zip_code": "68198-1090", "lat": 41.2555656, "lng": -95.97970579999999, "place_id": "ChIJ6ZAi2HmOk4cRywq2s2VxCqo", "national_drug_code": "0006-5055-06", "order_label": "Molnupiravir", "last_order_date": "2021-12-28T00:00:00", "last_delivered_date": null, "total_courses": 80, "courses_available": 80, "courses_available_date": "2022-01-05T00:00:00"}, {"provider_name": "Charles Drew Health Center", "address1": "2915 Grant Street", "address2": null, "city": "Omaha", "county": "Douglas", "state_code": "NE", "zip_code": "68111", "lat": 41.2795432, "lng": -95.9554005, "place_id": "ChIJN6wb8ySOk4cRhDnK0l6NE2s", "national_drug_code": "0006-5055-06", "order_label": "Molnupiravir", "last_order_date": "2021-12-28T00:00:00", "last_delivered_date": null, "total_courses": 100, "courses_available": null, "courses_available_date": null}, {"provider_name": "Nebraska Medicine", "address1": "981090 Nebraska Medical Center", "address2": "Buffett Dock", "city": "Omaha", "county": "Douglas", "state_code": "NE", "zip_code": "68198-1090", "lat": 41.2555656, "lng": -95.97970579999999, "place_id": "ChIJ6ZAi2HmOk4cRywq2s2VxCqo", "national_drug_code": "0310-7442-02", "order_label": "Evusheld", "last_order_date": "2021-12-18T00:00:00", "last_delivered_date": null, "total_courses": 96, "courses_available": 67, "courses_available_date": "2022-01-05T00:00:00"}, {"provider_name": "One World Health Centers", "address1": "4920 South 30th Street", "address2": "Suite 103", "city": "Omaha", "county": "Douglas", "state_code": "NE", "zip_code": "68107", "lat": 41.2100115, "lng": -95.95604689999999, "place_id": "ChIJd2YdY8yOk4cREGuafANMTCo", "national_drug_code": "0006-5055-06", "order_label": "Molnupiravir", "last_order_date": "2021-12-28T00:00:00", "last_delivered_date": null, "total_courses": 100, "courses_available": null, "courses_available_date": null}], "children": []}