{"path": ["FL", "Polk"], "total_courses": {"2022/01/05": {"Paxlovid": 140}, "2022/01/07": {"Paxlovid": 140}, "2022/01/10": {"Paxlovid": 140}, "2022/01/11": {"Paxlovid": 140}, "2022/01/12": {"Evusheld": 648, "Paxlovid": 140}, "2022/01/13": {"Evusheld": 648, "Paxlovid": 140}, "2022/01/14": {"Evusheld": 648, "Paxlovid": 140}, "2022/01/19": {"Evusheld": 936, "Paxlovid": 140}, "2022/01/21": {"Evusheld": 936, "Paxlovid": 140}, "2022/01/24": {"Evusheld": 936, "Paxlovid": 140}, "2022/01/25": {"Evusheld": 1872, "Paxlovid": 140}, "2022/01/26": {"Evusheld": 1872, "Paxlovid": 140}, "2022/01/27": {"Evusheld": 1872, "Paxlovid": 140}, "2022/01/28": {"Evusheld": 1872, "Paxlovid": 140}}, "courses_delivered": {"2022/01/05": {"Paxlovid": 140}, "2022/01/07": {"Paxlovid": 140}, "2022/01/10": {"Paxlovid": 0}, "2022/01/11": {"Paxlovid": 3}, "2022/01/12": {"Evusheld": 648, "Paxlovid": 3}, "2022/01/13": {"Evusheld": 648, "Paxlovid": 3}, "2022/01/14": {"Evusheld": 648, "Paxlovid": 9}, "2022/01/19": {"Evusheld": 936, "Paxlovid": 13}, "2022/01/21": {"Evusheld": 936, "Paxlovid": 21}, "2022/01/24": {"Evusheld": 936, "Paxlovid": 26}, "2022/01/25": {"Evusheld": 1872, "Paxlovid": 40}, "2022/01/26": {"Evusheld": 1872, "Paxlovid": 41}, "2022/01/27": {"Evusheld": 1872, "Paxlovid": 48}, "2022/01/28": {"Evusheld": 1872, "Paxlovid": 79}}, "courses_available": {"2022/01/05": {"Paxlovid": 0}, "2022/01/07": {"Paxlovid": 0}, "2022/01/10": {"Paxlovid": 140}, "2022/01/11": {"Paxlovid": 137}, "2022/01/12": {"Evusheld": 0, "Paxlovid": 137}, "2022/01/13": {"Evusheld": 0, "Paxlovid": 137}, "2022/01/14": {"Evusheld": 0, "Paxlovid": 131}, "2022/01/19": {"Evusheld": 0, "Paxlovid": 127}, "2022/01/21": {"Evusheld": 0, "Paxlovid": 119}, "2022/01/24": {"Evusheld": 0, "Paxlovid": 114}, "2022/01/25": {"Evusheld": 0, "Paxlovid": 100}, "2022/01/26": {"Evusheld": 0, "Paxlovid": 99}, "2022/01/27": {"Evusheld": 0, "Paxlovid": 92}, "2022/01/28": {"Evusheld": 0, "Paxlovid": 61}}, "children": {}, "child_treatments": [], "providers": {"2624": {"provider_name": "Walgreens Store #04005", "address1": "705 1st St S", "address2": null, "city": "Winter Haven", "county": "Polk", "state_code": "FL", "zip_code": "33880", "lat": 28.014496, "lng": -81.726845, "order_label": "Paxlovid"}}, "treatments": {"2624": {"Paxlovid": 61}}}