{"path": ["MI", "Mackinac"], "total_courses": {"2022/01/14": {"Paxlovid": 20}, "2022/01/19": {"Paxlovid": 20}, "2022/01/21": {"Paxlovid": 20}}, "courses_delivered": {"2022/01/14": {"Paxlovid": 16}, "2022/01/19": {"Paxlovid": 0}, "2022/01/21": {"Paxlovid": 0}}, "courses_available": {"2022/01/14": {"Paxlovid": 4}, "2022/01/19": {"Paxlovid": 24}, "2022/01/21": {"Paxlovid": 24}}, "children": {}, "child_treatments": [], "providers": {"239": {"provider_name": "Sault Tribal Health Human Svcs", "address1": "1140 N State St, Ste 2805", "address2": null, "city": "Saint Ignace", "county": "Mackinac", "state_code": "MI", "zip_code": "49781", "lat": 45.890989, "lng": -84.727559, "order_label": "Paxlovid"}}, "treatments": {"239": {"Paxlovid": 24}}}