{"path": ["TX", "Nacogdoches"], "total_courses": {"2022/01/05": {"Molnupiravir": 80, "Paxlovid": 20}, "2022/01/07": {"Molnupiravir": 80, "Paxlovid": 20}, "2022/01/10": {"Molnupiravir": 80, "Paxlovid": 20}, "2022/01/11": {"Molnupiravir": 80, "Paxlovid": 20}, "2022/01/12": {"Molnupiravir": 80, "Paxlovid": 20}, "2022/01/13": {"Molnupiravir": 80, "Paxlovid": 80}, "2022/01/14": {"Molnupiravir": 240, "Paxlovid": 80}, "2022/01/19": {"Molnupiravir": 240, "Paxlovid": 80}, "2022/01/21": {"Molnupiravir": 240, "Paxlovid": 80}}, "courses_delivered": {"2022/01/05": {"Molnupiravir": 10, "Paxlovid": 20}, "2022/01/07": {"Molnupiravir": 10, "Paxlovid": 20}, "2022/01/10": {"Molnupiravir": 16, "Paxlovid": 20}, "2022/01/11": {"Molnupiravir": 34, "Paxlovid": 20}, "2022/01/12": {"Molnupiravir": 36, "Paxlovid": 20}, "2022/01/13": {"Molnupiravir": 36, "Paxlovid": 60}, "2022/01/14": {"Molnupiravir": 214, "Paxlovid": 60}, "2022/01/19": {"Molnupiravir": 104, "Paxlovid": 22}, "2022/01/21": {"Molnupiravir": 131, "Paxlovid": 28}}, "courses_available": {"2022/01/05": {"Molnupiravir": 30, "Paxlovid": 0}, "2022/01/07": {"Molnupiravir": 30, "Paxlovid": 0}, "2022/01/10": {"Molnupiravir": 64, "Paxlovid": 0}, "2022/01/11": {"Molnupiravir": 46, "Paxlovid": 0}, "2022/01/12": {"Molnupiravir": 44, "Paxlovid": 0}, "2022/01/13": {"Molnupiravir": 44, "Paxlovid": 0}, "2022/01/14": {"Molnupiravir": 26, "Paxlovid": 0}, "2022/01/19": {"Molnupiravir": 136, "Paxlovid": 58}, "2022/01/21": {"Molnupiravir": 109, "Paxlovid": 52}}, "children": {}, "child_treatments": [], "providers": {"1907": {"provider_name": "Walmart Pharmacy #4674", "address1": "1030 N University Dr", "address2": null, "city": "Nacogdoches", "county": "Nacogdoches", "state_code": "TX", "zip_code": "75961", "lat": 31.61597, "lng": -94.639283, "order_label": "Paxlovid"}, "1908": {"provider_name": "Walgreens Store #09400", "address1": "3004 North St", "address2": null, "city": "Nacogdoches", "county": "Nacogdoches", "state_code": "TX", "zip_code": "75965", "lat": 31.631219, "lng": -94.652648, "order_label": "Molnupiravir"}, "1909": {"provider_name": "Walmart Pharmacy #163", "address1": "4810 North St", "address2": null, "city": "Nacogdoches", "county": "Nacogdoches", "state_code": "TX", "zip_code": "75965", "lat": 31.650323, "lng": -94.655614, "order_label": "Molnupiravir"}, "1910": {"provider_name": "Brookshires Pharmacy 42", "address1": "1420 N University Dr", "address2": null, "city": "Nacogdoches", "county": "Nacogdoches", "state_code": "TX", "zip_code": "75961", "lat": 31.61595, "lng": -94.63928, "order_label": "Molnupiravir"}}, "treatments": {"1907": {"Molnupiravir": 42, "Paxlovid": 19}, "1908": {"Paxlovid": 19, "Molnupiravir": 4}, "1909": {"Molnupiravir": 38}, "1910": {"Paxlovid": 14, "Molnupiravir": 25}}}