{"path": ["HI", "Honolulu"], "total_courses": {"2022/01/05": {"Evusheld": 480, "Molnupiravir": 580, "Paxlovid": 140}, "2022/01/07": {"Evusheld": 264, "Molnupiravir": 580, "Paxlovid": 140}, "2022/01/10": {"Evusheld": 456, "Molnupiravir": 420, "Paxlovid": 140}, "2022/01/11": {"Evusheld": 264, "Molnupiravir": 580, "Paxlovid": 160}, "2022/01/12": {"Evusheld": 336, "Molnupiravir": 700, "Paxlovid": 160}, "2022/01/13": {"Evusheld": 384, "Molnupiravir": 700, "Paxlovid": 180}}, "courses_delivered": {"2022/01/05": {"Evusheld": 168, "Molnupiravir": 320, "Paxlovid": 20}, "2022/01/07": {"Evusheld": 24, "Molnupiravir": 320, "Paxlovid": 20}, "2022/01/10": {"Evusheld": 28, "Molnupiravir": 300, "Paxlovid": 40}, "2022/01/11": {"Evusheld": 105, "Molnupiravir": 420, "Paxlovid": 29}, "2022/01/12": {"Evusheld": 174, "Molnupiravir": 160, "Paxlovid": 31}, "2022/01/13": {"Evusheld": 223, "Molnupiravir": 160, "Paxlovid": 35}}, "courses_available": {"2022/01/05": {"Evusheld": 144, "Molnupiravir": 0, "Paxlovid": 40}, "2022/01/07": {"Evusheld": 96, "Molnupiravir": 0, "Paxlovid": 20}, "2022/01/10": {"Evusheld": 260, "Molnupiravir": 0, "Paxlovid": 40}, "2022/01/11": {"Evusheld": 63, "Molnupiravir": 60, "Paxlovid": 71}, "2022/01/12": {"Evusheld": 42, "Molnupiravir": 380, "Paxlovid": 69}, "2022/01/13": {"Evusheld": 41, "Molnupiravir": 380, "Paxlovid": 65}}, "children": {}, "child_treatments": [], "providers": {"1022": {"provider_name": "Straub Medical Center Covid", "address1": "888 South King St", "address2": "Attn: Inpatient Pharmacy", "city": "Honolulu", "county": "Honolulu", "state_code": "HI", "zip_code": "96813", "lat": 21.302268, "lng": -157.850921, "order_label": "Molnupiravir"}, "1023": {"provider_name": "Kaiser Foundation Hospital", "address1": "3288 Moanalua Rd", "address2": null, "city": "Honolulu,", "county": "Honolulu", "state_code": "HI", "zip_code": "96819", "lat": 21.362447, "lng": -157.900297, "order_label": "Evusheld"}, "1024": {"provider_name": "Kokua Kalihi Valley", "address1": "2239 North School Street", "address2": null, "city": "Honolulu", "county": "Honolulu", "state_code": "HI", "zip_code": "96819", "lat": 21.340702, "lng": -157.874274, "order_label": "Paxlovid"}, "1025": {"provider_name": "Pharmerica - Honolulu 964", "address1": "3375 Koapaka St. Ste H-435", "address2": null, "city": "Honolulu", "county": "Honolulu", "state_code": "HI", "zip_code": "96819", "lat": 21.336366, "lng": -157.917412, "order_label": "Molnupiravir"}}, "treatments": {"1022": {"Paxlovid": 20, "Evusheld": 30, "Molnupiravir": 260}, "1023": {"Paxlovid": 15, "Molnupiravir": 60, "Evusheld": 11}, "1024": {"Paxlovid": 19}, "1025": {"Paxlovid": 11, "Molnupiravir": 60}}}