{"path": ["GA", "Muscogee"], "total_coures": {"2021/12/28": {"Evusheld": 0}, "2021/12/29": {"Evusheld": 0}, "2021/12/30": {"Evusheld": 0}, "2022/01/03": {"Evusheld": 144}, "2022/01/04": {"Evusheld": 144, "Molnupiravir": 200, "Paxlovid": 40}, "2022/01/05": {"Evusheld": 144, "Molnupiravir": 200, "Paxlovid": 40}}, "courses_delivered": {"2021/12/28": {"Evusheld": 0}, "2021/12/29": {"Evusheld": 0}, "2021/12/30": {"Evusheld": 0}, "2022/01/03": {"Evusheld": 96}, "2022/01/04": {"Evusheld": 96, "Molnupiravir": 0, "Paxlovid": 0}, "2022/01/05": {"Evusheld": 96, "Molnupiravir": 0, "Paxlovid": 0}}, "courses_available": {"2021/12/28": {"Evusheld": 0}, "2021/12/29": {"Evusheld": 0}, "2021/12/30": {"Evusheld": 0}, "2022/01/03": {"Evusheld": 48}, "2022/01/04": {"Evusheld": 48, "Molnupiravir": 0, "Paxlovid": 0}, "2022/01/05": {"Evusheld": 48, "Molnupiravir": 0, "Paxlovid": 0}}, "locations": [{"provider_name": "Piedmont Columbus Regional Midtown", "address1": "710 Center Street", "address2": "Dept Of Pharmacy", "city": "Columbus", "county": "Muscogee", "state_code": "GA", "zip_code": "31901", "lat": 32.480522, "lng": -84.9816665, "place_id": "ChIJLyFCeADNjIgR8iHqXtKPhv4", "national_drug_code": "0310-7442-02", "order_label": "Evusheld", "last_order_date": "2021-12-29T00:00:00", "last_delivered_date": null, "total_courses": 72, "courses_available": 24, "courses_available_date": "2022-01-05T00:00:00"}, {"provider_name": "Walmart Pharmacy #1338", "address1": "3515 Victory Dr", "address2": null, "city": "Columbus", "county": "Muscogee", "state_code": "GA", "zip_code": "31903", "lat": 32.4237865, "lng": -84.945661, "place_id": "ChIJ8-EU9LHSjIgRwn_mAIFawsY", "national_drug_code": "0006-5055-06", "order_label": "Molnupiravir", "last_order_date": "2021-12-30T00:00:00", "last_delivered_date": null, "total_courses": 100, "courses_available": null, "courses_available_date": null}, {"provider_name": "Piedmont Columbus Regional Midtown", "address1": "710 Center Street", "address2": "Dept Of Pharmacy", "city": "Columbus", "county": "Muscogee", "state_code": "GA", "zip_code": "31901", "lat": 32.480522, "lng": -84.9816665, "place_id": "ChIJLyFCeADNjIgR8iHqXtKPhv4", "national_drug_code": "0310-7442-02", "order_label": "Evusheld", "last_order_date": "2021-12-29T00:00:00", "last_delivered_date": null, "total_courses": 72, "courses_available": 24, "courses_available_date": "2022-01-05T00:00:00"}, {"provider_name": "Walmart Pharmacy #1311", "address1": "5448 Whittlesey Blvd Ste B", "address2": null, "city": "Columbus", "county": "Muscogee", "state_code": "GA", "zip_code": "31909", "lat": 32.5408574, "lng": -84.9484257, "place_id": "Ei81NDQ4IFdoaXR0bGVzZXkgQmx2ZCBiLCBDb2x1bWJ1cywgR0EgMzE5MDksIFVTQSIdGhsKFgoUChIJif4AB0_LjIgR3PtJoKXbqu0SAWI", "national_drug_code": "0006-5055-06", "order_label": "Molnupiravir", "last_order_date": "2021-12-30T00:00:00", "last_delivered_date": null, "total_courses": 100, "courses_available": null, "courses_available_date": null}, {"provider_name": "Walmart Pharmacy #1311", "address1": "5448 Whittlesey Blvd Ste B", "address2": null, "city": "Columbus", "county": "Muscogee", "state_code": "GA", "zip_code": "31909", "lat": 32.5408574, "lng": -84.9484257, "place_id": "Ei81NDQ4IFdoaXR0bGVzZXkgQmx2ZCBiLCBDb2x1bWJ1cywgR0EgMzE5MDksIFVTQSIdGhsKFgoUChIJif4AB0_LjIgR3PtJoKXbqu0SAWI", "national_drug_code": "0069-1085-30", "order_label": "Paxlovid", "last_order_date": "2021-12-30T00:00:00", "last_delivered_date": null, "total_courses": 20, "courses_available": null, "courses_available_date": null}, {"provider_name": "Walmart Pharmacy #1338", "address1": "3515 Victory Dr", "address2": null, "city": "Columbus", "county": "Muscogee", "state_code": "GA", "zip_code": "31903", "lat": 32.4237865, "lng": -84.945661, "place_id": "ChIJ8-EU9LHSjIgRwn_mAIFawsY", "national_drug_code": "0069-1085-30", "order_label": "Paxlovid", "last_order_date": "2021-12-30T00:00:00", "last_delivered_date": null, "total_courses": 20, "courses_available": null, "courses_available_date": null}], "children": []}