{"path": ["WV", "Mercer"], "total_courses": {"2022/01/05": {"Molnupiravir": 100, "Paxlovid": 20}, "2022/01/07": {"Molnupiravir": 100, "Paxlovid": 20}, "2022/01/10": {"Molnupiravir": 100, "Paxlovid": 20}, "2022/01/11": {"Molnupiravir": 100, "Paxlovid": 20}}, "courses_delivered": {"2022/01/05": {"Molnupiravir": 100, "Paxlovid": 20}, "2022/01/07": {"Molnupiravir": 100, "Paxlovid": 20}, "2022/01/10": {"Molnupiravir": 100, "Paxlovid": 20}, "2022/01/11": {"Molnupiravir": 100, "Paxlovid": 9}}, "courses_available": {"2022/01/05": {"Molnupiravir": 0, "Paxlovid": 0}, "2022/01/07": {"Molnupiravir": 0, "Paxlovid": 0}, "2022/01/10": {"Molnupiravir": 0, "Paxlovid": 0}, "2022/01/11": {"Molnupiravir": 0, "Paxlovid": 11}}, "children": {}, "child_treatments": [], "providers": {"1064": {"provider_name": "Walgreens Store #10876", "address1": "323 S Walker St", "address2": null, "city": "Princeton", "county": "Mercer", "state_code": "WV", "zip_code": "24740", "lat": 37.361459, "lng": -81.105016, "order_label": "Paxlovid"}}, "treatments": {"1064": {"Paxlovid": 11}}}