{"path": ["NV", "Carson City"], "total_courses": {"2022/01/05": {"Evusheld": 144, "Molnupiravir": 20}, "2022/01/07": {"Evusheld": 72, "Molnupiravir": 60}, "2022/01/10": {"Evusheld": 72, "Molnupiravir": 60}, "2022/01/11": {"Evusheld": 72, "Molnupiravir": 60}, "2022/01/12": {"Evusheld": 72, "Molnupiravir": 60}, "2022/01/13": {"Evusheld": 72, "Molnupiravir": 60, "Paxlovid": 40}, "2022/01/14": {"Evusheld": 96, "Molnupiravir": 140, "Paxlovid": 40}, "2022/01/19": {"Evusheld": 96, "Molnupiravir": 140, "Paxlovid": 40}}, "courses_delivered": {"2022/01/05": {"Evusheld": 0, "Molnupiravir": 0}, "2022/01/07": {"Evusheld": 0, "Molnupiravir": 0}, "2022/01/10": {"Evusheld": 0, "Molnupiravir": 0}, "2022/01/11": {"Evusheld": 0, "Molnupiravir": 0}, "2022/01/12": {"Evusheld": 0, "Molnupiravir": 1}, "2022/01/13": {"Evusheld": 0, "Molnupiravir": 1, "Paxlovid": 0}, "2022/01/14": {"Evusheld": 0, "Molnupiravir": 81, "Paxlovid": 0}, "2022/01/19": {"Evusheld": 0, "Molnupiravir": 2, "Paxlovid": 0}}, "courses_available": {"2022/01/05": {"Evusheld": 0, "Molnupiravir": 0}, "2022/01/07": {"Evusheld": 0, "Molnupiravir": 0}, "2022/01/10": {"Evusheld": 0, "Molnupiravir": 0}, "2022/01/11": {"Evusheld": 0, "Molnupiravir": 0}, "2022/01/12": {"Evusheld": 0, "Molnupiravir": 39}, "2022/01/13": {"Evusheld": 0, "Molnupiravir": 39, "Paxlovid": 0}, "2022/01/14": {"Evusheld": 0, "Molnupiravir": 59, "Paxlovid": 0}, "2022/01/19": {"Evusheld": 0, "Molnupiravir": 138, "Paxlovid": 0}}, "children": {}, "child_treatments": [], "providers": {"2739": {"provider_name": "Cvs Store #09842", "address1": "1980 N Carson St", "address2": "Cvs Pharmacy", "city": "Carson City", "county": "Carson City", "state_code": "NV", "zip_code": "89701", "lat": 39.178642, "lng": -119.76688, "order_label": "Molnupiravir"}, "2740": {"provider_name": "Walmart Pharmacy #3408", "address1": "3200 Market St", "address2": null, "city": "Carson City", "county": "Carson City", "state_code": "NV", "zip_code": "89706", "lat": 39.188873, "lng": -119.756382, "order_label": "Molnupiravir"}, "2741": {"provider_name": "Cvs Store #08779", "address1": "220 Fairview Lane", "address2": "Cvs Pharmacy", "city": "Carson City", "county": "Carson City", "state_code": "NV", "zip_code": "89701", "lat": 39.149933, "lng": -119.766174, "order_label": "Molnupiravir"}}, "treatments": {"2739": {"Molnupiravir": 60}, "2740": {"Molnupiravir": 20}, "2741": {"Molnupiravir": 58}}}