{"path": ["MI", "Allegan"], "total_courses": {"2021/12/28": {"Molnupiravir": 0}, "2021/12/29": {"Molnupiravir": 0}, "2021/12/30": {"Molnupiravir": 0}, "2022/01/03": {"Molnupiravir": 40}, "2022/01/04": {"Molnupiravir": 40}, "2022/01/05": {"Molnupiravir": 40}, "2022/01/07": {"Molnupiravir": 40}}, "courses_delivered": {"2021/12/28": {"Molnupiravir": 0}, "2021/12/29": {"Molnupiravir": 0}, "2021/12/30": {"Molnupiravir": 0}, "2022/01/03": {"Molnupiravir": 0}, "2022/01/04": {"Molnupiravir": 0}, "2022/01/05": {"Molnupiravir": 0}, "2022/01/07": {"Molnupiravir": 20}}, "courses_available": {"2021/12/28": {"Molnupiravir": 0}, "2021/12/29": {"Molnupiravir": 0}, "2021/12/30": {"Molnupiravir": 0}, "2022/01/03": {"Molnupiravir": 0}, "2022/01/04": {"Molnupiravir": 0}, "2022/01/05": {"Molnupiravir": 0}, "2022/01/07": {"Molnupiravir": 20}}, "children": {}, "child_treatments": [], "providers": {"ChIJ10qG3T5-F4gRktLz7Aq5iPA": {"provider_name": "Meijer Store 191", "address1": "1195 M 89", "address2": null, "city": "Plainwell", "county": "Allegan", "state_code": "MI", "zip_code": "49080", "lat": 42.4521738, "lng": -85.6605051, "place_id": "ChIJ10qG3T5-F4gRktLz7Aq5iPA", "order_label": "Molnupiravir"}}, "treatments": {"ChIJ10qG3T5-F4gRktLz7Aq5iPA": {"Molnupiravir": 20}}}