{"path": ["IN", "Montgomery"], "total_courses": {"2022/01/05": {"Molnupiravir": 40}, "2022/01/07": {"Molnupiravir": 40}, "2022/01/10": {"Molnupiravir": 40}, "2022/01/11": {"Molnupiravir": 40}}, "courses_delivered": {"2022/01/05": {"Molnupiravir": 0}, "2022/01/07": {"Molnupiravir": 0}, "2022/01/10": {"Molnupiravir": 0}, "2022/01/11": {"Molnupiravir": 0}}, "courses_available": {"2022/01/05": {"Molnupiravir": 0}, "2022/01/07": {"Molnupiravir": 0}, "2022/01/10": {"Molnupiravir": 40}, "2022/01/11": {"Molnupiravir": 40}}, "children": {}, "child_treatments": [], "providers": {"1815": {"provider_name": "Walmart Pharmacy #1655", "address1": "1835 S Us Highway 231", "address2": null, "city": "Crawfordsville", "county": "Montgomery", "state_code": "IN", "zip_code": "47933", "lat": 40.01278, "lng": -86.90385, "order_label": "Molnupiravir"}}, "treatments": {"1815": {"Molnupiravir": 40}}}