{"path": ["IL", "Mclean"], "total_courses": {"2022/01/13": {"Molnupiravir": 100, "Paxlovid": 20}, "2022/01/14": {"Molnupiravir": 100, "Paxlovid": 20}, "2022/01/19": {"Molnupiravir": 100, "Paxlovid": 20}, "2022/01/21": {"Molnupiravir": 100, "Paxlovid": 20}}, "courses_delivered": {"2022/01/13": {"Molnupiravir": 100, "Paxlovid": 20}, "2022/01/14": {"Molnupiravir": 100, "Paxlovid": 20}, "2022/01/19": {"Molnupiravir": 0, "Paxlovid": 0}, "2022/01/21": {"Molnupiravir": 0, "Paxlovid": 0}}, "courses_available": {"2022/01/13": {"Molnupiravir": 0, "Paxlovid": 0}, "2022/01/14": {"Molnupiravir": 0, "Paxlovid": 0}, "2022/01/19": {"Molnupiravir": 200, "Paxlovid": 40}, "2022/01/21": {"Molnupiravir": 200, "Paxlovid": 39}}, "children": {}, "child_treatments": [], "providers": {"337": {"provider_name": "Walgreens Store #15164", "address1": "2611 E Oakland Ave", "address2": null, "city": "Bloomington", "county": "Mclean", "state_code": "IL", "zip_code": "61701", "lat": 40.473536, "lng": -88.953309}}, "treatments": {"337": {"Molnupiravir": 200, "Paxlovid": 39}}}