{"path": ["NY", "Livingston"], "total_courses": {"2022/01/05": {"Evusheld": 24, "Molnupiravir": 80, "Paxlovid": 20}, "2022/01/07": {"Evusheld": 24, "Molnupiravir": 80, "Paxlovid": 20}, "2022/01/10": {"Evusheld": 24, "Molnupiravir": 80, "Paxlovid": 20}, "2022/01/11": {"Evusheld": 24, "Molnupiravir": 80, "Paxlovid": 20}, "2022/01/12": {"Evusheld": 24, "Molnupiravir": 80, "Paxlovid": 20}, "2022/01/13": {"Evusheld": 24, "Molnupiravir": 80, "Paxlovid": 20}, "2022/01/14": {"Evusheld": 24, "Molnupiravir": 80, "Paxlovid": 20}, "2022/01/19": {"Evusheld": 48, "Molnupiravir": 180, "Paxlovid": 60}, "2022/01/21": {"Evusheld": 48, "Molnupiravir": 180, "Paxlovid": 60}, "2022/01/24": {"Evusheld": 48, "Molnupiravir": 180, "Paxlovid": 60}, "2022/01/25": {"Evusheld": 72, "Molnupiravir": 280, "Paxlovid": 100}}, "courses_delivered": {"2022/01/05": {"Evusheld": 24, "Molnupiravir": 1, "Paxlovid": 4}, "2022/01/07": {"Evusheld": 24, "Molnupiravir": 1, "Paxlovid": 5}, "2022/01/10": {"Evusheld": 24, "Molnupiravir": 1, "Paxlovid": 6}, "2022/01/11": {"Evusheld": 24, "Molnupiravir": 1, "Paxlovid": 7}, "2022/01/12": {"Evusheld": 24, "Molnupiravir": 1, "Paxlovid": 7}, "2022/01/13": {"Evusheld": 24, "Molnupiravir": 1, "Paxlovid": 8}, "2022/01/14": {"Evusheld": 24, "Molnupiravir": 1, "Paxlovid": 9}, "2022/01/19": {"Evusheld": 48, "Molnupiravir": 101, "Paxlovid": 53}, "2022/01/21": {"Evusheld": 48, "Molnupiravir": 1, "Paxlovid": 15}, "2022/01/24": {"Evusheld": 48, "Molnupiravir": 2, "Paxlovid": 15}, "2022/01/25": {"Evusheld": 48, "Molnupiravir": 280, "Paxlovid": 59}}, "courses_available": {"2022/01/05": {"Evusheld": 0, "Molnupiravir": 79, "Paxlovid": 16}, "2022/01/07": {"Evusheld": 0, "Molnupiravir": 79, "Paxlovid": 15}, "2022/01/10": {"Evusheld": 0, "Molnupiravir": 79, "Paxlovid": 14}, "2022/01/11": {"Evusheld": 0, "Molnupiravir": 79, "Paxlovid": 13}, "2022/01/12": {"Evusheld": 0, "Molnupiravir": 79, "Paxlovid": 13}, "2022/01/13": {"Evusheld": 0, "Molnupiravir": 79, "Paxlovid": 12}, "2022/01/14": {"Evusheld": 0, "Molnupiravir": 79, "Paxlovid": 11}, "2022/01/19": {"Evusheld": 0, "Molnupiravir": 79, "Paxlovid": 7}, "2022/01/21": {"Evusheld": 0, "Molnupiravir": 179, "Paxlovid": 45}, "2022/01/24": {"Evusheld": 0, "Molnupiravir": 178, "Paxlovid": 45}, "2022/01/25": {"Evusheld": 24, "Molnupiravir": 0, "Paxlovid": 41}}, "children": {}, "child_treatments": [], "providers": {"2021": {"provider_name": "Cvs Store #05072", "address1": "225 Main St.,", "address2": "Cvs Pharmacy", "city": "Dansville", "county": "Livingston", "state_code": "NY", "zip_code": "14437", "lat": 42.562052, "lng": -77.697019}, "2022": {"provider_name": "Nicholas H Noyes Hospital", "address1": "111 Clara Barton St", "address2": "Attn: Dept Of Pharmacy", "city": "Dansville", "county": "Livingston", "state_code": "NY", "zip_code": "14437", "lat": 42.552038, "lng": -77.700314}}, "treatments": {"2021": {"Paxlovid": 41}, "2022": {"Evusheld": 24}}}