{"path": ["MS", "Grenada"], "total_coures": {"2022/01/04": {"Evusheld": 24}, "2022/01/05": {"Evusheld": 24}}, "courses_delivered": {"2022/01/04": {"Evusheld": 0}, "2022/01/05": {"Evusheld": 0}}, "courses_available": {"2022/01/04": {"Evusheld": 0}, "2022/01/05": {"Evusheld": 0}}, "locations": [{"provider_name": "Baptist Cancer Center Grenada", "address1": "1300 Sunset Drive", "address2": "Suite Q", "city": "Grenada", "county": "Grenada", "state_code": "MS", "zip_code": "38901", "lat": 33.7764916, "lng": -89.8223917, "place_id": "ChIJibWz1CLNgYgRBMpTeV2TbKE", "national_drug_code": "0310-7442-02", "order_label": "Evusheld", "last_order_date": "2021-12-28T00:00:00", "last_delivered_date": null, "total_courses": 24, "courses_available": null, "courses_available_date": null}], "children": []}